{
  "id": "gas",
  "sheetId": "",
  "name": "FlockOS-GAS",
  "shortName": "GAS",
  "brandName": "FlockOS-GAS",
  "tagline": "Ministry Operating System \u2014 Free. Offline-capable. Built for every church.",
  "favicon": "FlockOS_Orange.png",
  "portrait": "FlockOS_Orange.png",
  "themeColor": "#e8a838",
  "backgroundColor": "#1a1a2e",
  "databaseUrl": "https://script.google.com/macros/s/AKfycbwO3tVeCs6Ntf3udXNa-P0vhmUFFD1oeYR4kXXiI_evydp0yOeOESnHfYgx7r23JTEg/exec",
  "photosUrl": "",
  "adminEmail": "",
  "analyticsId": "",
  "firebaseConfig": null,
  "version": "3.0",
  "website": "gas.yhwh.one"
}
